agentr/__init__.py
agentr/application.py
agentr/cli.py
agentr/config.py
agentr/exceptions.py
agentr/integration.py
agentr/py.typed
agentr/server.py
agentr/store.py
agentr/test.py
agentr/applications/__init__.py
agentr/applications/github/app.py
agentr/applications/google_calendar/app.py
agentr/applications/google_mail/app.py
agentr/applications/reddit/app.py
agentr/applications/resend/app.py
agentr/applications/tavily/app.py
agentr/applications/zenquotes/app.py
agentr/integrations/README.md
agentr/integrations/__init__.py
agentr/integrations/agentr.py
agentr/integrations/api_key.py
agentr/integrations/base.py
agentr/utils/bridge.py
agentr/utils/openapi.py
agentr-0.1.9.dist-info/METADATA
agentr-0.1.9.dist-info/WHEEL
agentr-0.1.9.dist-info/entry_points.txt
agentr-0.1.9.dist-info/licenses/LICENSE
agentr-0.1.9.dist-info/RECORD
