Metadata-Version: 2.4
Name: agentr
Version: 0.1.9
Summary: An MCP middleware to connect to 400+ apps
Author-email: Manoj Bajaj <manoj@agentr.dev>
License-File: LICENSE
Requires-Python: >=3.11
Requires-Dist: loguru>=0.7.3
Requires-Dist: mcp>=1.5.0
Requires-Dist: pyyaml>=6.0.2
Requires-Dist: typer>=0.15.2
Provides-Extra: test
Requires-Dist: pytest-asyncio>=0.26.0; extra == 'test'
Requires-Dist: pytest>=8.3.5; extra == 'test'
